pretix_manualseats/__init__.py
pretix_manualseats/apps.py
pretix_manualseats/signals.py
pretix_manualseats/urls.py
pretix_manualseats/views.py
pretix_manualseats/locale/de/LC_MESSAGES/django.mo
pretix_manualseats/locale/de/LC_MESSAGES/django.po
pretix_manualseats/locale/de_Informal/LC_MESSAGES/django.mo
pretix_manualseats/locale/de_Informal/LC_MESSAGES/django.po
pretix_manualseats/static/pretix_manualseats/assignedseats-edit.js
pretix_manualseats/static/pretix_manualseats/seating-edit.js
pretix_manualseats/static/pretix_manualseats/icons/seat.svg
pretix_manualseats/templates/pretix_manualseats/event/assign.html
pretix_manualseats/templates/pretix_manualseats/event/index.html
pretix_manualseats/templates/pretix_manualseats/event/mapping.html
pretix_manualseats/templates/pretix_manualseats/organizer/delete.html
pretix_manualseats/templates/pretix_manualseats/organizer/form.html
pretix_manualseats/templates/pretix_manualseats/organizer/index.html
pretix_manualseats-1.0.5.dist-info/LICENSE
pretix_manualseats-1.0.5.dist-info/METADATA
pretix_manualseats-1.0.5.dist-info/WHEEL
pretix_manualseats-1.0.5.dist-info/entry_points.txt
pretix_manualseats-1.0.5.dist-info/top_level.txt
pretix_manualseats-1.0.5.dist-info/RECORD
