Metadata-Version: 2.1
Name: pretix-manualseats
Version: 1.0.5
Summary: Manually assign tickets to seats.
Author-email: Moritz Lerch <dev@moritz-lerch.de>
Maintainer-email: Moritz Lerch <dev@moritz-lerch.de>
License: 
Project-URL: homepage, https://github.com/moritzlerch/pretix-manualseats
Project-URL: repository, https://github.com/moritzlerch/pretix-manualseats
Keywords: pretix
Requires-Python: >=3.8
License-File: LICENSE
